LICENSE.txt
MANIFEST.in
README.rst
setup.cfg
setup.py
data/data_file
potholder/__init__.py
potholder.egg-info/PKG-INFO
potholder.egg-info/SOURCES.txt
potholder.egg-info/dependency_links.txt
potholder.egg-info/requires.txt
potholder.egg-info/top_level.txt
sample/__init__.py