Metadata-Version: 1.1
Name: potholder
Version: 0.0.2
Summary: Python interface for Potholder.
Home-page: https://github.com/Potholder/python-potholder
Author: Matvey Kukuy
Author-email: motakuk@gmail.com
License: MIT
Keywords: potholder
Platform: UNKNOWN
Classifier: Development Status :: 3 - Alpha
Classifier: Intended Audience :: Developers
Classifier: Topic :: Software Development :: Build Tools
Classifier: License :: OSI Approved :: MIT License
Classifier: Programming Language :: Python :: 2
Classifier: Programming Language :: Python :: 2.6
Classifier: Programming Language :: Python :: 2.7
Classifier: Programming Language :: Python :: 3
Classifier: Programming Language :: Python :: 3.3
Classifier: Programming Language :: Python :: 3.4
Classifier: Programming Language :: Python :: 3.5
